vianu/__init__.py
vianu/drugsafetycompare/__init__.py
vianu/drugsafetycompare/launch_demo_app.py
vianu/drugsafetycompare/launch_demo_pipeline.py
vianu/drugsafetycompare/settings.py
vianu/drugsafetycompare/src/__init__.py
vianu/drugsafetycompare/src/compare.py
vianu/drugsafetycompare/src/extract_germany.py
vianu/drugsafetycompare/src/extract_switzerland.py
vianu/drugsafetycompare/src/gpt_pipeline.py
vianu/drugsafetycompare/src/transformer_pipeline.py
vianu/fraudcrawler/.template_env
vianu/fraudcrawler/__init__.py
vianu/fraudcrawler/launch_demo_app.py
vianu/fraudcrawler/launch_demo_pipeline.py
vianu/fraudcrawler/settings.py
vianu/fraudcrawler/src/__init__.py
vianu/fraudcrawler/src/client.py
vianu/fraudcrawler/src/processor.py
vianu/fraudcrawler/src/serpapi.py
vianu/fraudcrawler/src/zyteapi.py
vianu/lasa/__init__.py
vianu/lasa/__main__.py
vianu/lasa/app/__init__.py
vianu/lasa/app/app.py
vianu/lasa/assets/css/styles.css
vianu/lasa/assets/images/bird.png
vianu/lasa/assets/images/logo-circular.png
vianu/lasa/assets/images/logo.png
vianu/lasa/assets/images/logo.webp
vianu/lasa/files/fda_products_20250121.csv
vianu/lasa/files/swissmedic_20241231.xlsx
vianu/lasa/launch_demo_app.py
vianu/lasa/launch_demo_pipeline.py
vianu/lasa/requirements.txt
vianu/lasa/settings.py
vianu/lasa/src/__init__.py
vianu/lasa/src/base.py
vianu/lasa/src/cli.py
vianu/lasa/src/units.py
vianu/newsscraper/README.md
vianu/newsscraper/envtemplate
vianu/newsscraper/launch_demo_app.py
vianu/newsscraper/src/db_manager.py
vianu/newsscraper/src/db_setup.py
vianu/newsscraper/src/entrypoint.sh
vianu/newsscraper/src/requirements.txt
vianu/newsscraper/src/run_scraper.py
vianu/newsscraper/src/run_scraper.sh
vianu/newsscraper/src/scrape.py
vianu/newsscraper/src/scraper_cron
vianu/spock/__init__.py
vianu/spock/__main__.py
vianu/spock/app/__init__.py
vianu/spock/app/app.py
vianu/spock/app/formatter.py
vianu/spock/assets/css/styles.css
vianu/spock/assets/head/scripts.html
vianu/spock/assets/images/favicon.png
vianu-0.1.4.dist-info/LICENSE
vianu-0.1.4.dist-info/METADATA
vianu-0.1.4.dist-info/WHEEL
vianu-0.1.4.dist-info/entry_points.txt
vianu-0.1.4.dist-info/RECORD
