Metadata-Version: 2.1
Name: vianu
Version: 0.1.4
Summary: Vianu enables developers to access tools applicable to life sciences and healthcare.
Home-page: https://github.com/smc40/vianu
License: MIT
Keywords: healthcare,government,opensource,data science
Author: Nicolas Perez Gonzalez
Author-email: hello@vianu.org
Requires-Python: >=3.11,<4.0
Classifier: License :: OSI Approved :: MIT License
Classifier: Programming Language :: Python :: 3
Classifier: Programming Language :: Python :: 3.11
Classifier: Programming Language :: Python :: 3.12
Requires-Dist: abydos (>=0.5.0,<0.6.0)
Requires-Dist: aiohttp (>=3.11.10,<4.0.0)
Requires-Dist: bandit (>=1.7.10,<2.0.0)
Requires-Dist: beautifulsoup4 (>=4.12.3,<5.0.0)
Requires-Dist: build (>=1.2.2.post1,<2.0.0)
Requires-Dist: cologne-phonetics (>=2.0.0,<3.0.0)
Requires-Dist: dacite (>=1.8.1,<2.0.0)
Requires-Dist: dateparser (>=1.2.0,<2.0.0)
Requires-Dist: defusedxml (>=0.7.1,<0.8.0)
Requires-Dist: gradio (>=5.11.0,<6.0.0)
Requires-Dist: llvmlite (>=0.43.0,<0.44.0)
Requires-Dist: matplotlib (>=3.9.3,<4.0.0)
Requires-Dist: numba (>=0.60.0,<0.61.0)
Requires-Dist: openai (>=1.59.5,<2.0.0)
Requires-Dist: openpyxl (>=3.1.5,<4.0.0)
Requires-Dist: pandas (>=2.2.3,<3.0.0)
Requires-Dist: pdfminer (>=20191125,<20191126)
Requires-Dist: plotly (>=5.24.1,<6.0.0)
Requires-Dist: pymupdf (>=1.25.1,<2.0.0)
Requires-Dist: pytest (>=8.3.4,<9.0.0)
Requires-Dist: pytest-cov (>=6.0.0,<7.0.0)
Requires-Dist: python-dotenv (>=1.0.1,<2.0.0)
Requires-Dist: selenium (>=4.27.1,<5.0.0)
Requires-Dist: shap (>=0.46.0,<0.47.0)
Requires-Dist: sqlitecloud (>=0.0.83,<0.0.84)
Requires-Dist: torch (>=2.5.1,<3.0.0)
Requires-Dist: transformers (>=4.46.3,<5.0.0)
Requires-Dist: twine (>=5.1.1,<6.0.0)
Project-URL: Repository, https://github.com/smc40/vianu
